vulnerability_scanner/__init__.py
vulnerability_scanner/__main__.py
vulnerability_scanner/modules/__init__.py
vulnerability_scanner/modules/broken_access_control.py
vulnerability_scanner/modules/cryptographic_failures.py
vulnerability_scanner/modules/identification_and_authentication_failures.py
vulnerability_scanner/modules/injection.py
vulnerability_scanner/modules/insecure_design.py
vulnerability_scanner/modules/security_misconfiguration.py
vulnerability_scanner/modules/semgrep_scanner.py
vulnerability_scanner/modules/software_and_data_integrity_failures.py
vulnerability_scanner/modules/ssrf.py
vulnerability_scanner/modules/vulnerable_and_outdated_components.py
vulnerability_scanner-0.1.2.dist-info/WHEEL
vulnerability_scanner-0.1.2.dist-info/entry_points.txt
vulnerability_scanner-0.1.2.dist-info/METADATA
vulnerability_scanner-0.1.2.dist-info/RECORD
