Metadata-Version: 2.3
Name: vulnerability-scanner
Version: 0.1.2
Summary: A developer-centric security toolkit that unifies multiple scanning engines (including a custom, AST-based Python scanner and Semgrep) to find OWASP Top 10 vulnerabilities. Designed for seamless integration into development workflows and CI/CD pipelines.
Requires-Dist: pip-audit>=2.9.0
Requires-Dist: semgrep>=1.133.0
Requires-Dist: typer>=0.16.0
Requires-Python: >=3.11
Project-URL: Bug Tracker, https://github.com/javieroc/vulnerability-scanner/issues
Project-URL: Homepage, https://github.com/javieroc/vulnerability-scanner
Project-URL: Repository, https://github.com/javieroc/vulnerability-scanner
